[
  {
    "ContainingType": "InspectionBackend.Controllers.UserControllers.AddUserController",
    "Method": "AddAccount",
    "RelativePath": "Api/Accounts/AddNewAccount",
    "HttpMethod": "POST",
    "IsController": true,
    "Order": 0,
    "Parameters": [
      {
        "Name": "dto",
        "Type": "InspectionBackend.Contracts.UserDtos.UserCreationRequest",
        "IsRequired": true
      }
    ],
    "ReturnTypes": []
  },
  {
    "ContainingType": "InspectionBackend.Controllers.UserControllers.LoginController",
    "Method": "AddAccount",
    "RelativePath": "Api/Accounts/Login",
    "HttpMethod": "POST",
    "IsController": true,
    "Order": 0,
    "Parameters": [
      {
        "Name": "dto",
        "Type": "InspectionBackend.Contracts.UserDtos.LoginRequest",
        "IsRequired": true
      }
    ],
    "ReturnTypes": []
  },
  {
    "ContainingType": "InspectionBackend.Controllers.UserControllers.TrainingController",
    "Method": "AddAccount",
    "RelativePath": "Api/Training/AddInspectionPattern",
    "HttpMethod": "POST",
    "IsController": true,
    "Order": 0,
    "Parameters": [
      {
        "Name": "dto",
        "Type": "InspectionBackend.Contracts.InspectionDtos.InspectionRequest",
        "IsRequired": true
      }
    ],
    "ReturnTypes": []
  },
  {
    "ContainingType": "InspectionBackend.Controllers.InspectionControllers.WebsraperController",
    "Method": "ImageRequest",
    "RelativePath": "Api/Training/Webscrape",
    "HttpMethod": "POST",
    "IsController": true,
    "Order": 0,
    "Parameters": [
      {
        "Name": "dto",
        "Type": "InspectionBackend.Contracts.InspectionDtos.InspectionImageRequest",
        "IsRequired": true
      }
    ],
    "ReturnTypes": []
  }
]